[{"idHouse": 0, "idLocation": 1, "name": "Khanh Uyen 3 Hotel", "address": "91 Phan B\u1ed9i Ch\u00e2u Ph\u01b0\u1eddng 1, \u0110\u00e0 L\u1ea1t, Vi\u00ea\u0323t Nam", "costOriginal": "VND 680.000", "costNew": "VND 408.000", "numberOfComment": "417 \u0111\u00e1nh gi\u00e1", "rate": "8,4", "label": "R\u1ea5t t\u1ed1t", "description": "B\u1ea1n \u0111\u1ee7 \u0111i\u1ec1u ki\u1ec7n nh\u1eadn gi\u1ea3m gi\u00e1 Genius t\u1ea1i Khanh Uyen 3 Hotel! \u0110\u1ec3 ti\u1ebft ki\u1ec7m t\u1ea1i ch\u1ed7 ngh\u1ec9 n\u00e0y, b\u1ea1n ch\u1ec9 c\u1ea7n\u0111\u0103ng nh\u1eadp.T\u1ecda l\u1ea1c t\u1ea1i th\u00e0nh ph\u1ed1 \u0110\u00e0 L\u1ea1t, c\u00e1ch Qu\u1ea3ng tr\u01b0\u1eddng L\u00e2m Vi\u00ean ch\u01b0a \u0111\u1ebfn 1 km v\u00e0 H\u1ed3 Xu\u00e2n H\u01b0\u01a1ng 11 ph\u00fat \u0111i b\u1ed9, Khanh Uyen 3 Hotel cung c\u1ea5p ch\u1ed7 ngh\u1ec9 v\u1edbi s\u1ea3nh kh\u00e1ch chung v\u00e0 WiFi mi\u1ec5n ph\u00ed c\u0169ng nh\u01b0 ch\u1ed7 \u0111\u1ed7 xe ri\u00eang mi\u1ec5n ph\u00ed cho kh\u00e1ch l\u00e1i xe. Ch\u1ed7 ngh\u1ec9 n\u00e0y c\u00f3 c\u00e1c ph\u00f2ng gia \u0111\u00ecnh v\u00e0 s\u00e2n hi\u00ean. Ch\u1ed7 ngh\u1ec9 cung c\u1ea5p d\u1ecbch v\u1ee5 l\u1ec5 t\u00e2n 24 gi\u1edd, d\u1ecbch v\u1ee5 ph\u00f2ng v\u00e0 d\u1ecbch v\u1ee5 thu \u0111\u1ed5i ngo\u1ea1i t\u1ec7 cho kh\u00e1ch.T\u1ea5t c\u1ea3 ph\u00f2ng ngh\u1ec9 c\u1ee7a kh\u00e1ch s\u1ea1n \u0111\u1ec1u c\u00f3 t\u1ee7 \u0111\u1ec3 qu\u1ea7n \u00e1o, TV m\u00e0n h\u00ecnh ph\u1eb3ng, ph\u00f2ng t\u1eafm ri\u00eang, ga tr\u1ea3i gi\u01b0\u1eddng v\u00e0 kh\u0103n t\u1eafm. Trong ph\u00f2ng \u0111\u01b0\u1ee3c trang b\u1ecb \u1ea5m \u0111un n\u01b0\u1edbc v\u00e0 t\u1ee7 l\u1ea1nh. M\u1ed9t s\u1ed1 ph\u00f2ng \u0111\u01b0\u1ee3c b\u1ed1 tr\u00ed b\u1ebfp v\u1edbi l\u00f2 vi s\u00f3ng v\u00e0 b\u1ebfp n\u1ea5u \u0103n.Trong s\u1ed1 c\u00e1c \u0111i\u1ec3m tham quan n\u1ed5i ti\u1ebfng g\u1ea7n Khanh Uyen 3 Hotel c\u00f3 C\u00f4ng vi\u00ean Yersin, V\u01b0\u1eddn hoa \u0110\u00e0 L\u1ea1t v\u00e0 Bi\u1ec7t th\u1ef1 H\u1eb1ng Nga (Ng\u00f4i nh\u00e0 \u0111i\u00ean). S\u00e2n bay g\u1ea7n nh\u1ea5t l\u00e0 s\u00e2n bay Li\u00ean Kh\u01b0\u01a1ng, c\u00e1ch \u0111\u00f3 23 km, v\u00e0 ch\u1ed7 ngh\u1ec9 cung c\u1ea5p d\u1ecbch v\u1ee5 \u0111\u01b0a \u0111\u00f3n s\u00e2n bay v\u1edbi m\u1ed9t kho\u1ea3n ph\u1ee5 ph\u00ed.\u0110\u00e2y l\u00e0 khu v\u1ef1c \u1edf \u0110\u00e0 L\u1ea1t m\u00e0 kh\u00e1ch y\u00eau th\u00edch, theo c\u00e1c \u0111\u00e1nh gi\u00e1 \u0111\u1ed9c l\u1eadp.C\u00e1c c\u1eb7p \u0111\u00f4i \u0111\u1eb7c bi\u1ec7t th\u00edch \u0111\u1ecba \u0111i\u1ec3m n\u00e0y \u2014 h\u1ecd cho \u0111i\u1ec3m9,3cho k\u1ef3 ngh\u1ec9 d\u00e0nh cho 2 ng\u01b0\u1eddi.Khanh Uyen 3 Hotel \u0111\u00e3 ch\u00e0o \u0111\u00f3n kh\u00e1ch Booking.com t\u1eeb Ng\u00e0y 16 Th\u00e1ng 4 N\u0103m 2021.C\u00e1c kho\u1ea3ng c\u00e1ch n\u00eau trong m\u00f4 t\u1ea3 ch\u1ed7 ngh\u1ec9 \u0111\u01b0\u1ee3c t\u00ednh to\u00e1n b\u1eb1ng \u00a9 OpenStreetMap", "images": null}]